encorelib/__init__.py
encorelib/encorelib.py
encorelib/test.py
encorelib/cli/__init__.py
encorelib/cli/utils.py
encorelib/datastructures/__init__.py
encorelib/datastructures/stack.py
encorelib/logging/__init__.py
encorelib/osmanager/__init__.py
encorelib/pbar/__init__.py
encorelib/plugins/__init__.py
encorelib/plugins/crypto_parser/__init__.py
encorelib/plugins/crypto_parser/cli.py
encorelib/timer/__init__.py
encorelib-0.1.1.dist-info/LICENSE
encorelib-0.1.1.dist-info/METADATA
encorelib-0.1.1.dist-info/WHEEL
encorelib-0.1.1.dist-info/top_level.txt
encorelib-0.1.1.dist-info/RECORD
