Metadata-Version: 2.1
Name: encorelib
Version: 0.1.1
Summary: This library contains several utilities for ecosystem products
Home-page: https://github.com/encore-ecosystem/speclib
Author: Encore Ecosystem
Author-email: meshushkevich.work@gmail.com
Project-URL: Documentation, https://github.com/encore-ecosystem/speclib
Keywords: cli menu terminal python encore
Classifier: Programming Language :: Python :: 3.9
Classifier: License :: OSI Approved :: MIT License
Classifier: Operating System :: OS Independent
Requires-Python: >=3.6
License-File: LICENSE
Requires-Dist: termcolor (~=2.2.0)
Requires-Dist: colorama (~=0.4.6)
